glibs-1.2.1-py3.10-nspkg.pth
glibs/exceptions.py
glibs/utils/__init__.py
glibs/utils/dictutils.py
glibs/utils/funcutils.py
glibs/utils/iterutils.py
glibs/utils/stringutils.py
glibs/utils/timeutils.py
glibs/utils/urlutils.py
glibs/utils/wwwutils.py
glibs-1.2.1.dist-info/METADATA
glibs-1.2.1.dist-info/WHEEL
glibs-1.2.1.dist-info/namespace_packages.txt
glibs-1.2.1.dist-info/top_level.txt
glibs-1.2.1.dist-info/RECORD
