Metadata-Version: 2.1
Name: glibs
Version: 1.2.1
Requires-Python: !=3.0.*,!=3.1.*,!=3.2.*,!=3.3.*,!=3.4.*,!=3.5.*,!=3.6.*,!=3.7.*,>=2.7
Requires-Dist: six (<2,>=1.16)
Provides-Extra: timeutils
Requires-Dist: ciso8601 (<2) ; extra == 'timeutils'
Requires-Dist: python-dateutil (<3,>=2.2) ; extra == 'timeutils'
